teraace_tracker/__init__.py
teraace_tracker/buffer.py
teraace_tracker/client.py
teraace_tracker/config.py
teraace_tracker/emitter.py
teraace_tracker/event_models.py
teraace_tracker/logging_util.py
teraace_tracker/shutdown.py
teraace_tracker/integrations/__init__.py
teraace_tracker/integrations/agentgpt.py
teraace_tracker/integrations/autogen.py
teraace_tracker/integrations/autogpt.py
teraace_tracker/integrations/babyagi.py
teraace_tracker/integrations/base.py
teraace_tracker/integrations/camel.py
teraace_tracker/integrations/crewai.py
teraace_tracker/integrations/dspy.py
teraace_tracker/integrations/haystack.py
teraace_tracker/integrations/instructor.py
teraace_tracker/integrations/langchain.py
teraace_tracker/integrations/llamaindex.py
teraace_tracker/integrations/metagpt.py
teraace_tracker/integrations/mirascope.py
teraace_tracker/integrations/phidata.py
teraace_tracker/integrations/pydantic_ai.py
teraace_tracker/integrations/rasa.py
teraace_tracker/integrations/semantic_kernel.py
teraace_tracker/integrations/superagi.py
teraace_tracker/integrations/swarm.py
teraace_tracker/integrations/taskweaver.py
teraace_tracker-1.1.8.dist-info/licenses/LICENSE
teraace_tracker-1.1.8.dist-info/METADATA
teraace_tracker-1.1.8.dist-info/WHEEL
teraace_tracker-1.1.8.dist-info/top_level.txt
teraace_tracker-1.1.8.dist-info/RECORD
