Metadata-Version: 2.4
Name: teraace-tracker
Version: 1.1.8
Summary: A comprehensive Python library for tracking AI agent events across LangChain, CrewAI, and AutoGPT frameworks
Author-email: Teraace <support@teraace.com>
Maintainer-email: Teraace Team <dev@teraace.com>
License: MIT
Project-URL: Homepage, https://www.teraace.com
Project-URL: Documentation, https://docs.teraace.com
Project-URL: Repository, https://github.com/hyepartners-gmail/teraace-tracker
Project-URL: Bug Tracker, https://github.com/hyepartners-gmail/teraace-tracker/issues
Keywords: ai,agents,tracking,monitoring,observability,langchain,crewai,autogpt,llm,machine-learning,analytics,telemetry,agentic,autonomous
Classifier: Development Status :: 5 - Production/Stable
Classifier: Intended Audience :: Developers
Classifier: Intended Audience :: Science/Research
Classifier: License :: OSI Approved :: MIT License
Classifier: Operating System :: OS Independent
Classifier: Programming Language :: Python :: 3
Classifier: Programming Language :: Python :: 3.8
Classifier: Programming Language :: Python :: 3.9
Classifier: Programming Language :: Python :: 3.10
Classifier: Programming Language :: Python :: 3.11
Classifier: Programming Language :: Python :: 3.12
Classifier: Programming Language :: Python :: 3 :: Only
Classifier: Topic :: Software Development :: Libraries :: Python Modules
Classifier: Topic :: Scientific/Engineering :: Artificial Intelligence
Classifier: Topic :: System :: Monitoring
Classifier: Topic :: System :: Logging
Classifier: Framework :: AsyncIO
Classifier: Typing :: Typed
Requires-Python: >=3.8
License-File: LICENSE
Requires-Dist: pydantic>=2.0.0
Requires-Dist: aiohttp>=3.8.0
Requires-Dist: python-dotenv>=1.0.0
Provides-Extra: langchain
Requires-Dist: langchain>=0.1.0; extra == "langchain"
Provides-Extra: crewai
Requires-Dist: crewai>=0.1.0; extra == "crewai"
Provides-Extra: autogpt
Requires-Dist: autogpt>=0.1.0; extra == "autogpt"
Provides-Extra: dev
Requires-Dist: pytest>=7.0.0; extra == "dev"
Requires-Dist: pytest-asyncio>=0.21.0; extra == "dev"
Requires-Dist: pytest-mock>=3.10.0; extra == "dev"
Requires-Dist: black>=23.0.0; extra == "dev"
Requires-Dist: isort>=5.12.0; extra == "dev"
Requires-Dist: flake8>=6.0.0; extra == "dev"
Requires-Dist: mypy>=1.0.0; extra == "dev"
Provides-Extra: all
Requires-Dist: langchain>=0.1.0; extra == "all"
Requires-Dist: crewai>=0.1.0; extra == "all"
Requires-Dist: autogpt>=0.1.0; extra == "all"
Dynamic: license-file
